monitering/__init__.py
monitering/check.py
monitering/collect.py
monitering/hello.py
monitering/run.py
monitering-0.0.5.dist-info/LICENSE
monitering-0.0.5.dist-info/METADATA
monitering-0.0.5.dist-info/WHEEL
monitering-0.0.5.dist-info/top_level.txt
monitering-0.0.5.dist-info/RECORD
