Metadata-Version: 2.1
Name: monitering
Version: 0.0.5
Summary: Real-time Trend Data Analysis/Monitoring System
Home-page: https://github.com/thisishoon/trend-monitoring
Author: Jihoon Kang
Author-email: jihoon522@naver.com
License: UNKNOWN
Keywords: trend,monitering
Platform: UNKNOWN
Classifier: Programming Language :: Python :: 3
Classifier: License :: OSI Approved :: MIT License
Classifier: Operating System :: OS Independent
Requires-Python: >=3
